ampdata/VERSION
ampdata/__init__.py
ampdata/auth.py
ampdata/curves.py
ampdata/events.py
ampdata/session.py
ampdata/util.py
ampdata-1.3.0.dist-info/LICENSE
ampdata-1.3.0.dist-info/METADATA
ampdata-1.3.0.dist-info/WHEEL
ampdata-1.3.0.dist-info/top_level.txt
ampdata-1.3.0.dist-info/RECORD
