Metadata-Version: 2.1
Name: ampdata
Version: 1.3.0
Summary: Ampiato AmpData Python library.
Home-page: https://ampiato.com.com
Author: Ampiato
Author-email: info@ampiato.com
License-File: LICENSE
Requires-Dist: requests >=2.18
Requires-Dist: sseclient-py >=1.7
Requires-Dist: pytz
Requires-Dist: pandas >=0.21
Requires-Dist: future >=0.16
Requires-Dist: python-dateutil
